Metadata-Version: 2.1
Name: aa-sbst
Version: 0.1.2
Summary: Self-balancing binary search tree
Home-page: https://github.com/amaslyaev/aa_sbst_py
Author: Alexander Maslyaev
Author-email: maslyaev@gmail.com
License: UNKNOWN
Project-URL: Bug Reports, https://github.com/amaslyaev/aa_sbst_py/issues
Project-URL: Source, https://github.com/amaslyaev/aa_sbst_py
Keywords: binary tree
Platform: UNKNOWN
Classifier: Development Status :: 4 - Beta
Classifier: Intended Audience :: Developers
Classifier: Intended Audience :: Education
Classifier: Topic :: Software Development :: Libraries
Classifier: License :: CC0 1.0 Universal (CC0 1.0) Public Domain Dedication
Classifier: Programming Language :: Python :: 3
Classifier: Programming Language :: Python :: 3.4
Classifier: Programming Language :: Python :: 3.5
Classifier: Programming Language :: Python :: 3.6
